create_reactpy_app/__init__.py
create_reactpy_app/__main__.py
create_reactpy_app/settings.py
create_reactpy_app-1.0.0.dist-info/LICENSE
create_reactpy_app-1.0.0.dist-info/METADATA
create_reactpy_app-1.0.0.dist-info/WHEEL
create_reactpy_app-1.0.0.dist-info/entry_points.txt
create_reactpy_app-1.0.0.dist-info/RECORD
