Metadata-Version: 2.1
Name: create-reactpy-app
Version: 1.0.0
Summary: 
License: GPL-3.0
Author: Minura Punchihewa
Author-email: minurapunchihewa17@gmail.com
Requires-Python: >=3.8,<4.0
Classifier: License :: OSI Approved :: GNU General Public License v3 (GPLv3)
Classifier: Programming Language :: Python :: 3
Classifier: Programming Language :: Python :: 3.8
Classifier: Programming Language :: Python :: 3.9
Classifier: Programming Language :: Python :: 3.10
Classifier: Programming Language :: Python :: 3.11
Requires-Dist: click (>=8.1.7,<9.0.0)
Requires-Dist: cookiecutter (>=2.6.0,<3.0.0)
Requires-Dist: pydantic-settings (>=2.2.1,<3.0.0)
